{
   "mixins": "stonehearth:mixins:item_properties",
   "type": "entity",
   "components": {
      "model_variants": {
         "default": {
            "layer": "armor",
            "models": [
               "file(maribor_forest.qb)"
            ]
         },
         "female": {
            "layer": "armor",
            "models": [
               "file(maribor_forest.qb)"
            ]
         }
      },
      "stonehearth:entity_forms": {
         "iconic_form": "file(maribor_forest_iconic.json)"
      },
      "stonehearth:equipment_piece": {
         "render_type": "merge_with_model",
         "slot": "maribor_forest",
         "ilevel": 1,
         "roles": ["witcher_job"],
         "equip_effect": "stonehearth:effects:weapon_level_up",
		 "injected_buffs": [
            "witchermod:buffs:maribor_forest"
         ]
      }
   },
   "entity_data": {
      "stonehearth:net_worth": {
         "value_in_gold": 23,
         "rarity": "common",
         "shop_info": {
            "buyable": false,
            "sellable": true,
            "shopkeeper_level": 1,
            "shopkeeper_type": "caravan"
         }
      },
	  "stonehearth:combat:melee_attacks": [
         {
            "name": "drink_maribor_forest",
            "effect": "drink_maribor_forest",
            "active_frame": 20,
            "cooldown": 24000,
            "priority": 3,
            "damage_multiplier": 0,
            "minimum_damage": 0
         }
      ],
      "stonehearth:catalog": {
         "display_name": "i18n(witchermod:entities.potion.maribor_forest.display_name)",
         "description": "i18n(witchermod:entities.potion.maribor_forest.description)",
         "icon": "file(maribor_forest.png)",
         "category": "armor",
         "material_tags": [
            "potion",
            "witchermod_made",
            "maribor_forest",
            "stockpile_equipment"
         ]
      }
   }
}
